{
  "url" : "http://127.0.0.1:8080/api/cells/a/a1e161f8-d405-4dde-b222-141712034fb8",
  "parentUrl" : null,
  "removed" : false,
  "position" : {
    "x" : 1.0632500350475311,
    "y" : 1.1435797668761438,
    "z" : -0.5631043165922165
  },
  "orientation" : {
    "x" : -0.017348679711686313,
    "y" : -0.6308332277949592,
    "z" : 0.18505165720830344,
    "w" : 0.7533288459205498
  },
  "scale" : {
    "x" : 0.125,
    "y" : 0.125,
    "z" : 0.125
  },
  "volatile" : false,
  "opacity" : 1.0,
  "shape" : "sphere",
  "texture" : "textures/gold.jpg"
}